suse_cloud_image_name_parser/__init__.py
suse_cloud_image_name_parser/errors.py
suse_cloud_image_name_parser/regex.py
suse_cloud_image_name_parser/suse_cloud_image_name.py
suse_cloud_image_name_parser-0.9.0.dist-info/licenses/LICENSE
suse_cloud_image_name_parser-0.9.0.dist-info/METADATA
suse_cloud_image_name_parser-0.9.0.dist-info/WHEEL
suse_cloud_image_name_parser-0.9.0.dist-info/top_level.txt
suse_cloud_image_name_parser-0.9.0.dist-info/RECORD
